id_api/__init__.py
id_api/core.py
id_api-0.1.1.dist-info/METADATA
id_api-0.1.1.dist-info/WHEEL
id_api-0.1.1.dist-info/top_level.txt
id_api-0.1.1.dist-info/RECORD
