Metadata-Version: 2.4
Name: id-api
Version: 0.1.1
Summary: Гибкая HTTP-клиентская библиотека с поддержкой JWT и OAuth2 аутентификации
Home-page: https://github.com/imdeniil/id-api
Author: Павлючик Даниил
Author-email: keemor821@gmail.com
Keywords: http client api jwt oauth2 async aiohttp requests
Classifier: Programming Language :: Python :: 3
Classifier: Programming Language :: Python :: 3.7
Classifier: Programming Language :: Python :: 3.8
Classifier: Programming Language :: Python :: 3.9
Classifier: Programming Language :: Python :: 3.10
Classifier: Programming Language :: Python :: 3.11
Classifier: License :: OSI Approved :: MIT License
Classifier: Operating System :: OS Independent
Classifier: Development Status :: 4 - Beta
Classifier: Intended Audience :: Developers
Classifier: Topic :: Software Development :: Libraries :: Python Modules
Classifier: Framework :: AsyncIO
Requires-Python: >=3.7
Requires-Dist: requests>=2.25.0
Requires-Dist: aiohttp>=3.7.0
Dynamic: author
Dynamic: author-email
Dynamic: classifier
Dynamic: description
Dynamic: description-content-type
Dynamic: home-page
Dynamic: keywords
Dynamic: requires-dist
Dynamic: requires-python
Dynamic: summary
